scrapeomatic/__init__.py
scrapeomatic/collector.py
scrapeomatic/collectors/__init__.py
scrapeomatic/collectors/github.py
scrapeomatic/collectors/instagram.py
scrapeomatic/collectors/threads.py
scrapeomatic/collectors/tiktok.py
scrapeomatic/collectors/twitter.py
scrapeomatic/collectors/youtube.py
scrapeomatic/tests/__init__.py
scrapeomatic/tests/test_github.py
scrapeomatic/tests/test_instagram.py
scrapeomatic/tests/test_threads.py
scrapeomatic/tests/test_tiktok.py
scrapeomatic/tests/test_twitter.py
scrapeomatic/tests/test_youtube.py
scrapeomatic/utils/__init__.py
scrapeomatic/utils/async_utils.py
scrapeomatic/utils/constants.py
scrapeomatic/utils/tiktok/__init__.py
scrapeomatic/utils/tiktok/xbogus.py
scrapeomatic-0.1.9.dist-info/LICENSE.txt
scrapeomatic-0.1.9.dist-info/METADATA
scrapeomatic-0.1.9.dist-info/WHEEL
scrapeomatic-0.1.9.dist-info/top_level.txt
scrapeomatic-0.1.9.dist-info/RECORD
