Metadata-Version: 2.1
Name: scrapeomatic
Version: 0.1.9
Home-page: https://github.com/geniza-ai/scrapomatic
Author: Charles S. Givre
Author-email: charles@geniza.ai
License: Apache-2.0
Classifier: Development Status :: 4 - Beta
Classifier: Intended Audience :: Developers
Classifier: Intended Audience :: System Administrators
Classifier: Intended Audience :: Science/Research
Classifier: License :: OSI Approved :: Apache Software License
Classifier: Programming Language :: Python
Classifier: Programming Language :: Python :: 3
Classifier: Programming Language :: SQL
Classifier: Operating System :: OS Independent
Classifier: Topic :: Internet
License-File: LICENSE.txt
Requires-Dist: selenium ~=4.14.0
Requires-Dist: bs4 ~=0.0.1
Requires-Dist: emoji ==2.8.0
Requires-Dist: requests ~=2.31.0
Requires-Dist: pandas ~=2.1.2
Requires-Dist: beautifulsoup4 ~=4.12.2
Requires-Dist: scrapetube ~=2.5.1
Requires-Dist: setuptools ~=68.2.0
Requires-Dist: playwright ~=1.40.0
Requires-Dist: requests-html-playwright ~=0.11.2
Requires-Dist: jmespath ~=1.0.1
Requires-Dist: ua-generator
Requires-Dist: parsel ==1.8.1
Requires-Dist: nested-lookup
Requires-Dist: html5lib
